odoo/addons/base_custom_system_parameter/README.rst
odoo/addons/base_custom_system_parameter/__init__.py
odoo/addons/base_custom_system_parameter/__manifest__.py
odoo/addons/base_custom_system_parameter/models/__init__.py
odoo/addons/base_custom_system_parameter/models/base_custom_system_parameter.py
odoo/addons/base_custom_system_parameter/security/ir.model.access.csv
odoo/addons/base_custom_system_parameter/static/description/icon.png
odoo/addons/base_custom_system_parameter/views/base_custom_system_parameter_views.xml
odoo14_addon_base_custom_system_parameter-14.0.1.0.1.dist-info/METADATA
odoo14_addon_base_custom_system_parameter-14.0.1.0.1.dist-info/WHEEL
odoo14_addon_base_custom_system_parameter-14.0.1.0.1.dist-info/top_level.txt
odoo14_addon_base_custom_system_parameter-14.0.1.0.1.dist-info/RECORD
