Metadata-Version: 2.1
Name: odoo14-addon-base-custom-system-parameter
Version: 14.0.1.0.1
Summary: Base Custom System Parameter
Home-page: https://simetri-sinergi.id
Author: PT. Simetri Sinergi Indonesia,OpenSynergy Indonesia
License: LGPL-3
Platform: UNKNOWN
Classifier: Programming Language :: Python
Classifier: Framework :: Odoo
Classifier: Framework :: Odoo :: 14.0
Classifier: License :: OSI Approved :: GNU Lesser General Public License v3 (LGPLv3)
Requires-Python: >=3.6
Requires-Dist: odoo (<14.1dev,>=14.0a)
